{"title":"한국일보 최진주 기자 ─ 네이버 뉴스","url":"https://media.naver.com/journalist/469/12963","favicon":"https://media.naver.com/journalist/469/favicon.ico","elements":[{"title":"日 정부, “미중 관계의 안정은 국제관계에서 지극히 중요”","contents":"<b>8시간전</b>","link":"https://n.news.naver.com/article/469/0000641496","retrieved":1637084437458,"image":"https://mimgnews.pstatic.net/image/origin/469/2021/11/16/641496.jpg?type=nf212_140"},{"title":"日 정부 반도체산업 지원 기금 만든다… 2030년 매출 3배 목표","contents":"<b>12시간전</b>","link":"https://n.news.naver.com/article/469/0000641415","retrieved":1637041033263,"image":"https://mimgnews.pstatic.net/image/origin/469/2021/11/16/641415.jpg?type=nf212_140"},{"title":"일본서 제기된 '델타 변이 자멸설'… 전문가 의견 분분","contents":"<b>1일전</b>","link":"https://n.news.naver.com/article/469/0000641268","retrieved":1636998288031,"image":"https://mimgnews.pstatic.net/image/origin/469/2021/11/15/641268.jpg?type=nf212_140"},{"title":"일본 7~9월 경제성장률 -0.8％… 코로나 긴급사태, 자동차 감산, 도쿄올림픽 특수 없었다","contents":"<b>1일전</b>","link":"https://n.news.naver.com/article/469/0000641189","retrieved":1636954635871,"image":"https://mimgnews.pstatic.net/image/origin/469/2021/11/15/641189.jpg?type=nf212_140"},{"title":"뉴욕에서 새 인생 시작한 일왕 조카 부부… “좋아하는 옷 사 입고 싶다”","contents":"<b>2일전</b>","link":"https://n.news.naver.com/article/469/0000641085","retrieved":1636911756597,"image":"https://mimgnews.pstatic.net/image/origin/469/2021/11/14/641085.jpg?type=nf212_140"},{"title":"日 경제안보 대비 본격화... “통신 설비 등 중국산 배제, 반도체 국내 확보”","contents":"<b>2일전</b>","link":"https://n.news.naver.com/article/469/0000641055","retrieved":1636911756598,"image":"https://mimgnews.pstatic.net/image/origin/469/2021/11/14/641055.jpg?type=nf212_140"},{"title":"‘아이는 쉽게 죽일 수 있어’ 日 어린이집 괴한 제압한 직원들[특파원 24시]","contents":"<b>2일전</b>","link":"https://n.news.naver.com/article/469/0000641041","retrieved":1637041033267,"image":"https://mimgnews.pstatic.net/image/origin/469/2021/11/14/641041.jpg?type=nf212_140"},{"title":"日 2차 기시다 내각 출범... 분배 정책, 대중 외교 ‘기시다 색깔 내기’ 본격화하나","contents":"<b>5일전</b>","link":"https://n.news.naver.com/article/469/0000640637","retrieved":1636652675885,"image":"https://mimgnews.pstatic.net/image/origin/469/2021/11/11/640637.jpg?type=nf212_140"},{"title":"하야시 日 외무 “한일 의사소통 가속” 징용·위안부 소송은 기존 입장 되풀이","contents":"<b>5일전</b>","link":"https://n.news.naver.com/article/469/0000640585","retrieved":1636652675886,"image":"https://mimgnews.pstatic.net/image/origin/469/2021/11/11/640585.jpg?type=nf212_140"},{"title":"‘물가 싼 일본’ 시대 끝나나...  수입물가 자국 내 제품 반영 현실화","contents":"<b>5일전</b>","link":"https://n.news.naver.com/article/469/0000640569","retrieved":1636652675886,"image":"https://mimgnews.pstatic.net/image/origin/469/2021/11/11/640569.jpg?type=nf212_140"}]}